{"cameraMode":{"drawMode":0,"name":"Shaded","section":"Shading Mode"},"sceneLighting":true,"audioPlay":false,"sceneViewState":{"m_AlwaysRefresh":false,"showFog":true,"showSkybox":true,"showFlares":true,"showImageEffects":true,"showParticleSystems":true,"showVisualEffectGraphs":true,"m_FxEnabled":true},"in2DMode":false,"pivot":{"x":3.0886764526367189,"y":-4.09100341796875,"z":-3.3552627563476564},"rotation":{"x":-0.20062978565692902,"y":0.4400682747364044,"z":-0.10155923664569855,"w":-0.8693530559539795},"size":53.53398132324219,"orthographic":false}